creator_en/__init__.py
creator_en/help.py
creator_en/input.py
creator_en/paginator.py
creator_en/py.typed
creator_en/embed_creator/__init__.py
creator_en/embed_creator/methods.py
embedcreator_en-0.0.5.dist-info/LICENSE
embedcreator_en-0.0.5.dist-info/METADATA
embedcreator_en-0.0.5.dist-info/WHEEL
embedcreator_en-0.0.5.dist-info/top_level.txt
embedcreator_en-0.0.5.dist-info/RECORD
