Metadata-Version: 2.1
Name: embedcreator-en
Version: 0.0.5
Author: Leticia Sousa
Author-email: leticialimasousa2007@gmail.com
License: MIT License
License-File: LICENSE
Requires-Dist: discord.py
